fastmcp_sqltools/__init__.py
fastmcp_sqltools/server.py
fastmcp_sqltools-0.3.0.dist-info/METADATA
fastmcp_sqltools-0.3.0.dist-info/WHEEL
fastmcp_sqltools-0.3.0.dist-info/entry_points.txt
fastmcp_sqltools-0.3.0.dist-info/licenses/LICENSE
fastmcp_sqltools-0.3.0.dist-info/RECORD
