Metadata-Version: 2.4
Name: fastmcp-sqltools
Version: 0.3.0
Summary: FastMCP SQL server with support for PostgreSQL, MySQL, and SQLite
Author-email: Ola Tarkowska <ola@entrypoint.tech>
License-File: LICENSE
Classifier: Intended Audience :: Developers
Classifier: Programming Language :: Python :: 3
Classifier: Programming Language :: Python :: 3.10
Classifier: Programming Language :: Python :: 3.11
Classifier: Programming Language :: Python :: 3.12
Requires-Python: >=3.10
Requires-Dist: aiomysql
Requires-Dist: aiosqlite
Requires-Dist: asyncpg
Requires-Dist: fastmcp
Provides-Extra: dev
Requires-Dist: pytest-asyncio>=0.21.0; extra == 'dev'
Requires-Dist: pytest-cov>=4.1.0; extra == 'dev'
Requires-Dist: pytest>=7.4.0; extra == 'dev'
Requires-Dist: reportlab>=4.0.0; extra == 'dev'
